CHANGES.rst
LICENSE
MANIFEST.in
README.rst
setup.cfg
setup.py
tox.ini
morepath_static/__init__.py
morepath_static/__main__.py
morepath_static/app.py
morepath_static/model.py
morepath_static/path.py
morepath_static/static.py
morepath_static/view.py
morepath_static.egg-info/PKG-INFO
morepath_static.egg-info/SOURCES.txt
morepath_static.egg-info/dependency_links.txt
morepath_static.egg-info/entry_points.txt
morepath_static.egg-info/not-zip-safe
morepath_static.egg-info/requires.txt
morepath_static.egg-info/top_level.txt
morepath_static/bower_components/jquery/.bower.json
morepath_static/bower_components/jquery/MIT-LICENSE.txt
morepath_static/bower_components/jquery/bower.json
morepath_static/bower_components/jquery/dist/jquery.js
morepath_static/bower_components/jquery/dist/jquery.min.js
morepath_static/bower_components/jquery/dist/jquery.min.map
morepath_static/my_component/bower.json
morepath_static/my_component/main.js
morepath_static/tests/__init__.py
morepath_static/tests/test_morepath_static.py